.gitattributes
.gitignore
LICENSE
MANIFEST.in
README.md
requirements.txt
setup.py
.github/workflows/linter.yaml
.github/workflows/python-publish.yaml
.github/workflows/test.yaml
chikkarpy/__init__.py
chikkarpy/chikkar.py
chikkarpy/command_line.py
chikkarpy/config.py
chikkarpy/synonym.py
chikkarpy/synonymgroup.py
chikkarpy.egg-info/PKG-INFO
chikkarpy.egg-info/SOURCES.txt
chikkarpy.egg-info/dependency_links.txt
chikkarpy.egg-info/entry_points.txt
chikkarpy.egg-info/requires.txt
chikkarpy.egg-info/top_level.txt
chikkarpy/dictionarylib/__init__.py
chikkarpy/dictionarylib/binarydictionary.py
chikkarpy/dictionarylib/dictionary.py
chikkarpy/dictionarylib/dictionarybuilder.py
chikkarpy/dictionarylib/dictionaryheader.py
chikkarpy/dictionarylib/dictionaryversion.py
chikkarpy/dictionarylib/doublearraytrie.py
chikkarpy/dictionarylib/flags.py
chikkarpy/dictionarylib/idtable.py
chikkarpy/dictionarylib/jtypedbytebuffer.py
chikkarpy/dictionarylib/synonym_group_list.py
chikkarpy/dictionarylib/format/__init__.py
chikkarpy/dictionarylib/format/format.py
scripts/flake8.cfg
scripts/license-header.txt
scripts/lint.sh
scripts/test.sh
tests/__init__.py
tests/test_chikkar.py
tests/test_synonymgroup.py
tests/dictionarylib/__init__.py
tests/dictionarylib/test_dictionary.py
tests/dictionarylib/test_dictionaryheader.py
tests/dictionarylib/test_doublearraytrie.py
tests/dictionarylib/test_flags.py
tests/resources/system.csv
tests/resources/user.csv
tests/resources/user2.csv