Metadata-Version: 2.1
Name: chikkarpy
Version: 0.1.1
Summary: Python version of chikkar, a library for using the Sudachi synonym dictionary
Home-page: https://github.com/WorksApplications/chikkarpy
Author: Works Applications
Author-email: sudachi@worksap.co.jp
License: Apache-2.0
Platform: UNKNOWN
License-File: LICENSE
